lino_noi/__init__.py
lino_noi/lib/__init__.py
lino_noi/lib/cal/__init__.py
lino_noi/lib/cal/models.py
lino_noi/lib/cal/fixtures/__init__.py
lino_noi/lib/cal/fixtures/demo.py
lino_noi/lib/cal/fixtures/demo2.py
lino_noi/lib/cal/fixtures/std.py
lino_noi/lib/contacts/__init__.py
lino_noi/lib/contacts/models.py
lino_noi/lib/contacts/fixtures/__init__.py
lino_noi/lib/contacts/fixtures/demo.py
lino_noi/lib/contacts/fixtures/std.py
lino_noi/lib/courses/__init__.py
lino_noi/lib/courses/models.py
lino_noi/lib/courses/ui.py
lino_noi/lib/groups/__init__.py
lino_noi/lib/groups/models.py
lino_noi/lib/noi/__init__.py
lino_noi/lib/noi/help_texts.py
lino_noi/lib/noi/layouts.py
lino_noi/lib/noi/migrate.py
lino_noi/lib/noi/models.py
lino_noi/lib/noi/settings.py
lino_noi/lib/noi/user_types.py
lino_noi/lib/noi/workflows.py
lino_noi/lib/noi/fixtures/__init__.py
lino_noi/lib/noi/fixtures/demo.py
lino_noi/lib/noi/fixtures/demo2.py
lino_noi/lib/noi/fixtures/demo_bookings.py
lino_noi/lib/noi/fixtures/linotickets.py
lino_noi/lib/noi/fixtures/minimal_ledger.py
lino_noi/lib/noi/locale/django.pot
lino_noi/lib/noi/locale/de/LC_MESSAGES/django.mo
lino_noi/lib/noi/locale/de/LC_MESSAGES/django.po
lino_noi/lib/noi/locale/et/LC_MESSAGES/django.mo
lino_noi/lib/noi/locale/et/LC_MESSAGES/django.po
lino_noi/lib/noi/locale/fr/LC_MESSAGES/django.mo
lino_noi/lib/noi/locale/fr/LC_MESSAGES/django.po
lino_noi/lib/products/__init__.py
lino_noi/lib/products/models.py
lino_noi/lib/subscriptions/__init__.py
lino_noi/lib/subscriptions/models.py
lino_noi/lib/tickets/__init__.py
lino_noi/lib/tickets/models.py
lino_noi/lib/tickets/workflows.py
lino_noi/lib/trading/__init__.py
lino_noi/lib/trading/models.py
lino_noi/lib/trading/config/trading/VatProductInvoice/noi.weasy.html
lino_noi/lib/trading/fixtures/__init__.py
lino_noi/lib/trading/fixtures/std.py
lino_noi/lib/users/__init__.py
lino_noi/lib/users/models.py
lino_noi/lib/users/ui.py
lino_noi/lib/users/fixtures/__init__.py
lino_noi/lib/users/fixtures/demo.py
lino_noi-26.1.0.dist-info/METADATA
lino_noi-26.1.0.dist-info/WHEEL
lino_noi-26.1.0.dist-info/licenses/COPYING
lino_noi-26.1.0.dist-info/RECORD
